gpttranslator/__init__.py
gpttranslator/translator.py
gpttranslator-0.1.0.dist-info/LICENSE
gpttranslator-0.1.0.dist-info/METADATA
gpttranslator-0.1.0.dist-info/WHEEL
gpttranslator-0.1.0.dist-info/top_level.txt
gpttranslator-0.1.0.dist-info/RECORD
